{
  "ticker": "TSLA",
  "company_name": "Tesla, Inc.",
  "current_price": 438.07,
  "previous_close": 449.72,
  "day_high": 458.33,
  "day_low": 435.3,
  "fifty_two_week_high": 498.83,
  "fifty_two_week_low": 214.25,
  "volume": 84769853,
  "avg_volume": 80861561,
  "market_cap": 1456941563904,
  "pe_ratio": 302.11725,
  "dividend_yield": "N/A",
  "historical_data": [
    {
      "date": "2025-01-03",
      "open": 381.48,
      "high": 411.88,
      "low": 379.45,
      "close": 410.44,
      "volume": 95423300,
      "adjClose": 410.44
    },
    {
      "date": "2025-01-06",
      "open": 423.2,
      "high": 426.43,
      "low": 401.7,
      "close": 411.05,
      "volume": 85516500,
      "adjClose": 411.05
    },
    {
      "date": "2025-01-07",
      "open": 405.83,
      "high": 414.33,
      "low": 390.0,
      "close": 394.36,
      "volume": 75699500,
      "adjClose": 394.36
    },
    {
      "date": "2025-01-08",
      "open": 392.95,
      "high": 402.5,
      "low": 387.4,
      "close": 394.94,
      "volume": 73038800,
      "adjClose": 394.94
    },
    {
      "date": "2025-01-10",
      "open": 391.4,
      "high": 399.28,
      "low": 377.29,
      "close": 394.74,
      "volume": 62287300,
      "adjClose": 394.74
    },
    {
      "date": "2025-01-13",
      "open": 383.21,
      "high": 403.79,
      "low": 380.07,
      "close": 403.31,
      "volume": 67580500,
      "adjClose": 403.31
    },
    {
      "date": "2025-01-14",
      "open": 414.34,
      "high": 422.64,
      "low": 394.54,
      "close": 396.36,
      "volume": 84565000,
      "adjClose": 396.36
    },
    {
      "date": "2025-01-15",
      "open": 409.9,
      "high": 429.8,
      "low": 405.66,
      "close": 428.22,
      "volume": 81375500,
      "adjClose": 428.22
    },
    {
      "date": "2025-01-16",
      "open": 423.49,
      "high": 424.0,
      "low": 409.13,
      "close": 413.82,
      "volume": 68335200,
      "adjClose": 413.82
    },
    {
      "date": "2025-01-17",
      "open": 421.5,
      "high": 439.74,
      "low": 419.75,
      "close": 426.5,
      "volume": 94991400,
      "adjClose": 426.5
    },
    {
      "date": "2025-01-21",
      "open": 432.64,
      "high": 433.2,
      "low": 406.31,
      "close": 424.07,
      "volume": 87320900,
      "adjClose": 424.07
    },
    {
      "date": "2025-01-22",
      "open": 416.81,
      "high": 428.0,
      "low": 414.59,
      "close": 415.11,
      "volume": 60963300,
      "adjClose": 415.11
    },
    {
      "date": "2025-01-23",
      "open": 416.06,
      "high": 420.73,
      "low": 408.95,
      "close": 412.38,
      "volume": 50690600,
      "adjClose": 412.38
    },
    {
      "date": "2025-01-24",
      "open": 414.45,
      "high": 418.88,
      "low": 405.78,
      "close": 406.58,
      "volume": 56427100,
      "adjClose": 406.58
    },
    {
      "date": "2025-01-27",
      "open": 394.8,
      "high": 406.69,
      "low": 389.0,
      "close": 397.15,
      "volume": 58125500,
      "adjClose": 397.15
    },
    {
      "date": "2025-01-28",
      "open": 396.91,
      "high": 400.59,
      "low": 386.5,
      "close": 398.09,
      "volume": 48910700,
      "adjClose": 398.09
    },
    {
      "date": "2025-01-29",
      "open": 395.21,
      "high": 398.59,
      "low": 384.48,
      "close": 389.1,
      "volume": 68033600,
      "adjClose": 389.1
    },
    {
      "date": "2025-01-30",
      "open": 410.78,
      "high": 412.5,
      "low": 384.41,
      "close": 400.28,
      "volume": 98092900,
      "adjClose": 400.28
    },
    {
      "date": "2025-01-31",
      "open": 401.53,
      "high": 419.99,
      "low": 401.34,
      "close": 404.6,
      "volume": 83283600,
      "adjClose": 404.6
    },
    {
      "date": "2025-02-03",
      "open": 386.68,
      "high": 389.17,
      "low": 374.36,
      "close": 383.68,
      "volume": 93732100,
      "adjClose": 383.68
    },
    {
      "date": "2025-02-04",
      "open": 382.63,
      "high": 394.0,
      "low": 381.4,
      "close": 392.21,
      "volume": 57072200,
      "adjClose": 392.21
    },
    {
      "date": "2025-02-05",
      "open": 387.51,
      "high": 388.39,
      "low": 375.53,
      "close": 378.17,
      "volume": 57223300,
      "adjClose": 378.17
    },
    {
      "date": "2025-02-06",
      "open": 373.03,
      "high": 375.4,
      "low": 363.18,
      "close": 374.32,
      "volume": 77918200,
      "adjClose": 374.32
    },
    {
      "date": "2025-02-07",
      "open": 370.19,
      "high": 380.55,
      "low": 360.34,
      "close": 361.62,
      "volume": 70298300,
      "adjClose": 361.62
    },
    {
      "date": "2025-02-10",
      "open": 356.21,
      "high": 362.7,
      "low": 350.51,
      "close": 350.73,
      "volume": 77514900,
      "adjClose": 350.73
    },
    {
      "date": "2025-02-11",
      "open": 345.8,
      "high": 349.37,
      "low": 325.1,
      "close": 328.5,
      "volume": 118543400,
      "adjClose": 328.5
    },
    {
      "date": "2025-02-12",
      "open": 329.94,
      "high": 346.4,
      "low": 329.12,
      "close": 336.51,
      "volume": 105382700,
      "adjClose": 336.51
    },
    {
      "date": "2025-02-13",
      "open": 345.0,
      "high": 358.69,
      "low": 342.85,
      "close": 355.94,
      "volume": 89441500,
      "adjClose": 355.94
    },
    {
      "date": "2025-02-14",
      "open": 360.62,
      "high": 362.0,
      "low": 347.5,
      "close": 355.84,
      "volume": 68277300,
      "adjClose": 355.84
    },
    {
      "date": "2025-02-18",
      "open": 355.01,
      "high": 359.1,
      "low": 350.02,
      "close": 354.11,
      "volume": 51631700,
      "adjClose": 354.11
    },
    {
      "date": "2025-02-19",
      "open": 354.0,
      "high": 367.34,
      "low": 353.67,
      "close": 360.56,
      "volume": 67094400,
      "adjClose": 360.56
    },
    {
      "date": "2025-02-20",
      "open": 361.51,
      "high": 362.3,
      "low": 348.0,
      "close": 354.4,
      "volume": 45965400,
      "adjClose": 354.4
    },
    {
      "date": "2025-02-21",
      "open": 353.44,
      "high": 354.98,
      "low": 334.42,
      "close": 337.8,
      "volume": 74058600,
      "adjClose": 337.8
    },
    {
      "date": "2025-02-24",
      "open": 338.14,
      "high": 342.4,
      "low": 324.7,
      "close": 330.53,
      "volume": 76052300,
      "adjClose": 330.53
    },
    {
      "date": "2025-02-25",
      "open": 327.02,
      "high": 328.89,
      "low": 297.25,
      "close": 302.8,
      "volume": 134228800,
      "adjClose": 302.8
    },
    {
      "date": "2025-02-26",
      "open": 303.71,
      "high": 309.0,
      "low": 288.04,
      "close": 290.8,
      "volume": 100118300,
      "adjClose": 290.8
    },
    {
      "date": "2025-02-27",
      "open": 291.16,
      "high": 297.23,
      "low": 280.88,
      "close": 281.95,
      "volume": 101748200,
      "adjClose": 281.95
    },
    {
      "date": "2025-02-28",
      "open": 279.5,
      "high": 293.88,
      "low": 273.6,
      "close": 292.98,
      "volume": 115697000,
      "adjClose": 292.98
    },
    {
      "date": "2025-03-03",
      "open": 300.34,
      "high": 303.94,
      "low": 277.3,
      "close": 284.65,
      "volume": 115551400,
      "adjClose": 284.65
    },
    {
      "date": "2025-03-04",
      "open": 270.93,
      "high": 284.35,
      "low": 261.84,
      "close": 272.04,
      "volume": 126706600,
      "adjClose": 272.04
    },
    {
      "date": "2025-03-05",
      "open": 272.92,
      "high": 279.55,
      "low": 267.71,
      "close": 279.1,
      "volume": 94042900,
      "adjClose": 279.1
    },
    {
      "date": "2025-03-06",
      "open": 272.06,
      "high": 272.65,
      "low": 260.02,
      "close": 263.45,
      "volume": 98451600,
      "adjClose": 263.45
    },
    {
      "date": "2025-03-07",
      "open": 259.32,
      "high": 266.25,
      "low": 250.73,
      "close": 262.67,
      "volume": 102369600,
      "adjClose": 262.67
    },
    {
      "date": "2025-03-10",
      "open": 252.54,
      "high": 253.37,
      "low": 220.0,
      "close": 222.15,
      "volume": 189076900,
      "adjClose": 222.15
    },
    {
      "date": "2025-03-11",
      "open": 225.31,
      "high": 237.06,
      "low": 217.02,
      "close": 230.58,
      "volume": 174896400,
      "adjClose": 230.58
    },
    {
      "date": "2025-03-12",
      "open": 247.22,
      "high": 251.84,
      "low": 241.1,
      "close": 248.09,
      "volume": 142215700,
      "adjClose": 248.09
    },
    {
      "date": "2025-03-13",
      "open": 248.13,
      "high": 248.29,
      "low": 232.6,
      "close": 240.68,
      "volume": 114813500,
      "adjClose": 240.68
    },
    {
      "date": "2025-03-14",
      "open": 247.31,
      "high": 251.58,
      "low": 240.73,
      "close": 249.98,
      "volume": 100242300,
      "adjClose": 249.98
    },
    {
      "date": "2025-03-17",
      "open": 245.06,
      "high": 245.4,
      "low": 232.8,
      "close": 238.01,
      "volume": 111900600,
      "adjClose": 238.01
    },
    {
      "date": "2025-03-18",
      "open": 228.16,
      "high": 230.1,
      "low": 222.28,
      "close": 225.31,
      "volume": 111477600,
      "adjClose": 225.31
    },
    {
      "date": "2025-03-19",
      "open": 231.61,
      "high": 241.41,
      "low": 229.2,
      "close": 235.86,
      "volume": 111993800,
      "adjClose": 235.86
    },
    {
      "date": "2025-03-20",
      "open": 233.35,
      "high": 238.0,
      "low": 230.05,
      "close": 236.26,
      "volume": 99028300,
      "adjClose": 236.26
    },
    {
      "date": "2025-03-21",
      "open": 234.99,
      "high": 249.52,
      "low": 234.55,
      "close": 248.71,
      "volume": 132728700,
      "adjClose": 248.71
    },
    {
      "date": "2025-03-24",
      "open": 258.08,
      "high": 278.64,
      "low": 256.33,
      "close": 278.39,
      "volume": 169079900,
      "adjClose": 278.39
    },
    {
      "date": "2025-03-25",
      "open": 283.6,
      "high": 288.2,
      "low": 271.28,
      "close": 288.14,
      "volume": 150361500,
      "adjClose": 288.14
    },
    {
      "date": "2025-03-26",
      "open": 282.66,
      "high": 284.9,
      "low": 266.51,
      "close": 272.06,
      "volume": 153629800,
      "adjClose": 272.06
    },
    {
      "date": "2025-03-27",
      "open": 272.48,
      "high": 291.85,
      "low": 271.82,
      "close": 273.13,
      "volume": 162572100,
      "adjClose": 273.13
    },
    {
      "date": "2025-03-28",
      "open": 275.58,
      "high": 276.1,
      "low": 260.57,
      "close": 263.55,
      "volume": 123809400,
      "adjClose": 263.55
    },
    {
      "date": "2025-03-31",
      "open": 249.31,
      "high": 260.56,
      "low": 243.36,
      "close": 259.16,
      "volume": 134008900,
      "adjClose": 259.16
    },
    {
      "date": "2025-04-01",
      "open": 263.8,
      "high": 277.45,
      "low": 259.25,
      "close": 268.46,
      "volume": 146486900,
      "adjClose": 268.46
    },
    {
      "date": "2025-04-02",
      "open": 254.6,
      "high": 284.99,
      "low": 251.27,
      "close": 282.76,
      "volume": 212787800,
      "adjClose": 282.76
    },
    {
      "date": "2025-04-03",
      "open": 265.29,
      "high": 276.3,
      "low": 261.51,
      "close": 267.28,
      "volume": 136174300,
      "adjClose": 267.28
    },
    {
      "date": "2025-04-04",
      "open": 255.38,
      "high": 261.0,
      "low": 236.0,
      "close": 239.43,
      "volume": 181229400,
      "adjClose": 239.43
    },
    {
      "date": "2025-04-07",
      "open": 223.78,
      "high": 252.0,
      "low": 214.25,
      "close": 233.29,
      "volume": 183453800,
      "adjClose": 233.29
    },
    {
      "date": "2025-04-08",
      "open": 245.0,
      "high": 250.44,
      "low": 217.8,
      "close": 221.86,
      "volume": 171603500,
      "adjClose": 221.86
    },
    {
      "date": "2025-04-09",
      "open": 224.69,
      "high": 274.69,
      "low": 223.88,
      "close": 272.2,
      "volume": 219433400,
      "adjClose": 272.2
    },
    {
      "date": "2025-04-10",
      "open": 260.0,
      "high": 262.49,
      "low": 239.33,
      "close": 252.4,
      "volume": 181722600,
      "adjClose": 252.4
    },
    {
      "date": "2025-04-11",
      "open": 251.84,
      "high": 257.74,
      "low": 241.36,
      "close": 252.31,
      "volume": 128948100,
      "adjClose": 252.31
    },
    {
      "date": "2025-04-14",
      "open": 258.36,
      "high": 261.8,
      "low": 245.93,
      "close": 252.35,
      "volume": 100135200,
      "adjClose": 252.35
    },
    {
      "date": "2025-04-15",
      "open": 249.91,
      "high": 258.75,
      "low": 247.54,
      "close": 254.11,
      "volume": 79594300,
      "adjClose": 254.11
    },
    {
      "date": "2025-04-16",
      "open": 247.61,
      "high": 251.97,
      "low": 233.89,
      "close": 241.55,
      "volume": 112378700,
      "adjClose": 241.55
    },
    {
      "date": "2025-04-17",
      "open": 243.47,
      "high": 244.34,
      "low": 237.68,
      "close": 241.37,
      "volume": 83404800,
      "adjClose": 241.37
    },
    {
      "date": "2025-04-21",
      "open": 230.26,
      "high": 232.21,
      "low": 222.79,
      "close": 227.5,
      "volume": 97768000,
      "adjClose": 227.5
    },
    {
      "date": "2025-04-22",
      "open": 230.96,
      "high": 242.79,
      "low": 229.85,
      "close": 237.97,
      "volume": 120858500,
      "adjClose": 237.97
    },
    {
      "date": "2025-04-23",
      "open": 254.86,
      "high": 259.45,
      "low": 244.43,
      "close": 250.74,
      "volume": 150381900,
      "adjClose": 250.74
    },
    {
      "date": "2025-04-24",
      "open": 250.5,
      "high": 259.54,
      "low": 249.2,
      "close": 259.51,
      "volume": 94464200,
      "adjClose": 259.51
    },
    {
      "date": "2025-04-25",
      "open": 261.69,
      "high": 286.85,
      "low": 259.63,
      "close": 284.95,
      "volume": 167560700,
      "adjClose": 284.95
    },
    {
      "date": "2025-04-28",
      "open": 288.98,
      "high": 294.86,
      "low": 272.42,
      "close": 285.88,
      "volume": 151731800,
      "adjClose": 285.88
    },
    {
      "date": "2025-04-29",
      "open": 285.5,
      "high": 293.32,
      "low": 279.47,
      "close": 292.03,
      "volume": 108906600,
      "adjClose": 292.03
    },
    {
      "date": "2025-04-30",
      "open": 279.9,
      "high": 284.45,
      "low": 270.78,
      "close": 282.16,
      "volume": 128961100,
      "adjClose": 282.16
    },
    {
      "date": "2025-05-01",
      "open": 280.01,
      "high": 290.87,
      "low": 279.81,
      "close": 280.52,
      "volume": 99659000,
      "adjClose": 280.52
    },
    {
      "date": "2025-05-02",
      "open": 284.9,
      "high": 294.78,
      "low": 279.81,
      "close": 287.21,
      "volume": 114454700,
      "adjClose": 287.21
    },
    {
      "date": "2025-05-05",
      "open": 284.57,
      "high": 284.85,
      "low": 274.4,
      "close": 280.26,
      "volume": 94618900,
      "adjClose": 280.26
    },
    {
      "date": "2025-05-06",
      "open": 273.11,
      "high": 277.73,
      "low": 271.35,
      "close": 275.35,
      "volume": 76715800,
      "adjClose": 275.35
    },
    {
      "date": "2025-05-07",
      "open": 276.88,
      "high": 277.92,
      "low": 271.0,
      "close": 276.22,
      "volume": 71592600,
      "adjClose": 276.22
    },
    {
      "date": "2025-05-08",
      "open": 279.63,
      "high": 289.8,
      "low": 279.41,
      "close": 284.82,
      "volume": 97539400,
      "adjClose": 284.82
    },
    {
      "date": "2025-05-09",
      "open": 290.21,
      "high": 307.04,
      "low": 290.0,
      "close": 298.26,
      "volume": 132387800,
      "adjClose": 298.26
    },
    {
      "date": "2025-05-12",
      "open": 321.99,
      "high": 322.21,
      "low": 311.5,
      "close": 318.38,
      "volume": 112826700,
      "adjClose": 318.38
    },
    {
      "date": "2025-05-13",
      "open": 320.0,
      "high": 337.59,
      "low": 316.8,
      "close": 334.07,
      "volume": 136992600,
      "adjClose": 334.07
    },
    {
      "date": "2025-05-14",
      "open": 342.5,
      "high": 350.0,
      "low": 337.0,
      "close": 347.68,
      "volume": 136997300,
      "adjClose": 347.68
    },
    {
      "date": "2025-05-15",
      "open": 340.34,
      "high": 346.14,
      "low": 334.72,
      "close": 342.82,
      "volume": 97882600,
      "adjClose": 342.82
    },
    {
      "date": "2025-05-16",
      "open": 346.24,
      "high": 351.62,
      "low": 342.33,
      "close": 349.98,
      "volume": 95895700,
      "adjClose": 349.98
    },
    {
      "date": "2025-05-19",
      "open": 336.3,
      "high": 343.0,
      "low": 333.37,
      "close": 342.09,
      "volume": 88869900,
      "adjClose": 342.09
    },
    {
      "date": "2025-05-20",
      "open": 347.87,
      "high": 354.99,
      "low": 341.63,
      "close": 343.82,
      "volume": 131715500,
      "adjClose": 343.82
    },
    {
      "date": "2025-05-21",
      "open": 344.43,
      "high": 347.35,
      "low": 332.2,
      "close": 334.62,
      "volume": 102354800,
      "adjClose": 334.62
    },
    {
      "date": "2025-05-22",
      "open": 331.9,
      "high": 347.27,
      "low": 331.39,
      "close": 341.04,
      "volume": 97113400,
      "adjClose": 341.04
    },
    {
      "date": "2025-05-23",
      "open": 337.92,
      "high": 343.18,
      "low": 333.21,
      "close": 339.34,
      "volume": 84654800,
      "adjClose": 339.34
    },
    {
      "date": "2025-05-27",
      "open": 347.35,
      "high": 363.79,
      "low": 347.32,
      "close": 362.89,
      "volume": 120146400,
      "adjClose": 362.89
    },
    {
      "date": "2025-05-28",
      "open": 364.84,
      "high": 365.0,
      "low": 355.91,
      "close": 356.9,
      "volume": 91404300,
      "adjClose": 356.9
    },
    {
      "date": "2025-05-29",
      "open": 365.29,
      "high": 367.71,
      "low": 356.0,
      "close": 358.43,
      "volume": 88087800,
      "adjClose": 358.43
    },
    {
      "date": "2025-05-30",
      "open": 355.52,
      "high": 363.68,
      "low": 345.29,
      "close": 346.46,
      "volume": 123474900,
      "adjClose": 346.46
    },
    {
      "date": "2025-06-02",
      "open": 343.5,
      "high": 348.02,
      "low": 333.33,
      "close": 342.69,
      "volume": 81873800,
      "adjClose": 342.69
    },
    {
      "date": "2025-06-03",
      "open": 346.6,
      "high": 355.4,
      "low": 343.04,
      "close": 344.27,
      "volume": 99324500,
      "adjClose": 344.27
    },
    {
      "date": "2025-06-04",
      "open": 345.1,
      "high": 345.6,
      "low": 327.33,
      "close": 332.05,
      "volume": 98912100,
      "adjClose": 332.05
    },
    {
      "date": "2025-06-05",
      "open": 322.49,
      "high": 324.55,
      "low": 273.21,
      "close": 284.7,
      "volume": 287499800,
      "adjClose": 284.7
    },
    {
      "date": "2025-06-06",
      "open": 298.83,
      "high": 305.5,
      "low": 291.14,
      "close": 295.14,
      "volume": 164747700,
      "adjClose": 295.14
    },
    {
      "date": "2025-06-09",
      "open": 285.96,
      "high": 309.83,
      "low": 281.85,
      "close": 308.58,
      "volume": 140908900,
      "adjClose": 308.58
    },
    {
      "date": "2025-06-10",
      "open": 314.94,
      "high": 327.83,
      "low": 310.67,
      "close": 326.09,
      "volume": 151256500,
      "adjClose": 326.09
    },
    {
      "date": "2025-06-11",
      "open": 334.4,
      "high": 335.5,
      "low": 322.5,
      "close": 326.43,
      "volume": 122611400,
      "adjClose": 326.43
    },
    {
      "date": "2025-06-12",
      "open": 323.08,
      "high": 332.56,
      "low": 316.86,
      "close": 319.11,
      "volume": 105127500,
      "adjClose": 319.11
    },
    {
      "date": "2025-06-13",
      "open": 313.97,
      "high": 332.99,
      "low": 313.3,
      "close": 325.31,
      "volume": 128964300,
      "adjClose": 325.31
    },
    {
      "date": "2025-06-16",
      "open": 331.29,
      "high": 332.05,
      "low": 326.41,
      "close": 329.13,
      "volume": 83925900,
      "adjClose": 329.13
    },
    {
      "date": "2025-06-17",
      "open": 326.09,
      "high": 327.26,
      "low": 314.74,
      "close": 316.35,
      "volume": 88282700,
      "adjClose": 316.35
    },
    {
      "date": "2025-06-18",
      "open": 317.31,
      "high": 329.32,
      "low": 315.45,
      "close": 322.05,
      "volume": 95137700,
      "adjClose": 322.05
    },
    {
      "date": "2025-06-20",
      "open": 327.95,
      "high": 332.36,
      "low": 317.78,
      "close": 322.16,
      "volume": 108688000,
      "adjClose": 322.16
    },
    {
      "date": "2025-06-23",
      "open": 327.54,
      "high": 357.54,
      "low": 327.48,
      "close": 348.68,
      "volume": 190716800,
      "adjClose": 348.68
    },
    {
      "date": "2025-06-24",
      "open": 356.17,
      "high": 356.26,
      "low": 340.44,
      "close": 340.47,
      "volume": 114736200,
      "adjClose": 340.47
    },
    {
      "date": "2025-06-25",
      "open": 342.7,
      "high": 343.0,
      "low": 320.4,
      "close": 327.55,
      "volume": 119845100,
      "adjClose": 327.55
    },
    {
      "date": "2025-06-26",
      "open": 324.61,
      "high": 331.05,
      "low": 323.61,
      "close": 325.78,
      "volume": 80440900,
      "adjClose": 325.78
    },
    {
      "date": "2025-06-27",
      "open": 324.51,
      "high": 329.34,
      "low": 317.5,
      "close": 323.63,
      "volume": 89067000,
      "adjClose": 323.63
    },
    {
      "date": "2025-06-30",
      "open": 319.9,
      "high": 325.58,
      "low": 316.6,
      "close": 317.66,
      "volume": 76695100,
      "adjClose": 317.66
    },
    {
      "date": "2025-07-01",
      "open": 298.46,
      "high": 305.89,
      "low": 293.21,
      "close": 300.71,
      "volume": 145085700,
      "adjClose": 300.71
    },
    {
      "date": "2025-07-02",
      "open": 312.63,
      "high": 316.83,
      "low": 303.82,
      "close": 315.65,
      "volume": 119483700,
      "adjClose": 315.65
    },
    {
      "date": "2025-07-03",
      "open": 317.99,
      "high": 318.45,
      "low": 312.76,
      "close": 315.35,
      "volume": 58042300,
      "adjClose": 315.35
    },
    {
      "date": "2025-07-07",
      "open": 291.37,
      "high": 296.15,
      "low": 288.77,
      "close": 293.94,
      "volume": 131177900,
      "adjClose": 293.94
    },
    {
      "date": "2025-07-08",
      "open": 297.0,
      "high": 304.05,
      "low": 294.35,
      "close": 297.81,
      "volume": 103246700,
      "adjClose": 297.81
    },
    {
      "date": "2025-07-09",
      "open": 297.55,
      "high": 300.15,
      "low": 293.55,
      "close": 295.88,
      "volume": 75586800,
      "adjClose": 295.88
    },
    {
      "date": "2025-07-10",
      "open": 300.05,
      "high": 310.48,
      "low": 300.0,
      "close": 309.87,
      "volume": 104365300,
      "adjClose": 309.87
    },
    {
      "date": "2025-07-11",
      "open": 307.89,
      "high": 314.09,
      "low": 305.65,
      "close": 313.51,
      "volume": 79236400,
      "adjClose": 313.51
    },
    {
      "date": "2025-07-14",
      "open": 317.73,
      "high": 322.6,
      "low": 312.67,
      "close": 316.9,
      "volume": 78043400,
      "adjClose": 316.9
    },
    {
      "date": "2025-07-15",
      "open": 319.68,
      "high": 321.2,
      "low": 310.5,
      "close": 310.78,
      "volume": 77556300,
      "adjClose": 310.78
    },
    {
      "date": "2025-07-16",
      "open": 312.8,
      "high": 323.5,
      "low": 312.62,
      "close": 321.67,
      "volume": 97284800,
      "adjClose": 321.67
    },
    {
      "date": "2025-07-17",
      "open": 323.15,
      "high": 324.34,
      "low": 317.06,
      "close": 319.41,
      "volume": 73922900,
      "adjClose": 319.41
    },
    {
      "date": "2025-07-18",
      "open": 321.66,
      "high": 330.9,
      "low": 321.42,
      "close": 329.65,
      "volume": 94255000,
      "adjClose": 329.65
    },
    {
      "date": "2025-07-21",
      "open": 334.4,
      "high": 338.0,
      "low": 326.88,
      "close": 328.49,
      "volume": 75768800,
      "adjClose": 328.49
    },
    {
      "date": "2025-07-22",
      "open": 329.74,
      "high": 335.41,
      "low": 321.55,
      "close": 332.11,
      "volume": 77370400,
      "adjClose": 332.11
    },
    {
      "date": "2025-07-23",
      "open": 330.9,
      "high": 336.2,
      "low": 328.67,
      "close": 332.56,
      "volume": 92553800,
      "adjClose": 332.56
    },
    {
      "date": "2025-07-24",
      "open": 310.0,
      "high": 310.15,
      "low": 300.41,
      "close": 305.3,
      "volume": 156966000,
      "adjClose": 305.3
    },
    {
      "date": "2025-07-25",
      "open": 308.74,
      "high": 323.63,
      "low": 308.01,
      "close": 316.06,
      "volume": 148227000,
      "adjClose": 316.06
    },
    {
      "date": "2025-07-28",
      "open": 318.45,
      "high": 330.49,
      "low": 315.69,
      "close": 325.59,
      "volume": 112673800,
      "adjClose": 325.59
    },
    {
      "date": "2025-07-29",
      "open": 325.55,
      "high": 326.25,
      "low": 318.25,
      "close": 321.2,
      "volume": 87358900,
      "adjClose": 321.2
    },
    {
      "date": "2025-07-30",
      "open": 322.18,
      "high": 324.45,
      "low": 311.62,
      "close": 319.04,
      "volume": 83931900,
      "adjClose": 319.04
    },
    {
      "date": "2025-07-31",
      "open": 319.61,
      "high": 321.37,
      "low": 306.1,
      "close": 308.27,
      "volume": 85270900,
      "adjClose": 308.27
    },
    {
      "date": "2025-08-01",
      "open": 306.21,
      "high": 309.31,
      "low": 297.82,
      "close": 302.63,
      "volume": 89121400,
      "adjClose": 302.63
    },
    {
      "date": "2025-08-04",
      "open": 309.08,
      "high": 312.12,
      "low": 303.0,
      "close": 309.26,
      "volume": 78683900,
      "adjClose": 309.26
    },
    {
      "date": "2025-08-05",
      "open": 308.95,
      "high": 312.45,
      "low": 305.5,
      "close": 308.72,
      "volume": 57961300,
      "adjClose": 308.72
    },
    {
      "date": "2025-08-06",
      "open": 307.89,
      "high": 320.47,
      "low": 306.93,
      "close": 319.91,
      "volume": 78523600,
      "adjClose": 319.91
    },
    {
      "date": "2025-08-07",
      "open": 319.79,
      "high": 322.4,
      "low": 316.16,
      "close": 322.27,
      "volume": 66658700,
      "adjClose": 322.27
    },
    {
      "date": "2025-08-08",
      "open": 321.43,
      "high": 335.15,
      "low": 320.98,
      "close": 329.65,
      "volume": 91200300,
      "adjClose": 329.65
    },
    {
      "date": "2025-08-11",
      "open": 335.0,
      "high": 346.64,
      "low": 334.15,
      "close": 339.03,
      "volume": 105320200,
      "adjClose": 339.03
    },
    {
      "date": "2025-08-12",
      "open": 345.0,
      "high": 345.26,
      "low": 332.94,
      "close": 340.84,
      "volume": 80522100,
      "adjClose": 340.84
    },
    {
      "date": "2025-08-13",
      "open": 341.5,
      "high": 348.98,
      "low": 338.2,
      "close": 339.38,
      "volume": 67838900,
      "adjClose": 339.38
    },
    {
      "date": "2025-08-14",
      "open": 335.76,
      "high": 340.47,
      "low": 330.4,
      "close": 335.58,
      "volume": 75000700,
      "adjClose": 335.58
    },
    {
      "date": "2025-08-15",
      "open": 337.66,
      "high": 339.3,
      "low": 327.02,
      "close": 330.56,
      "volume": 74319800,
      "adjClose": 330.56
    },
    {
      "date": "2025-08-18",
      "open": 329.62,
      "high": 336.27,
      "low": 329.59,
      "close": 335.16,
      "volume": 56956600,
      "adjClose": 335.16
    },
    {
      "date": "2025-08-19",
      "open": 335.79,
      "high": 340.55,
      "low": 327.85,
      "close": 329.31,
      "volume": 75956000,
      "adjClose": 329.31
    },
    {
      "date": "2025-08-20",
      "open": 329.22,
      "high": 331.37,
      "low": 314.6,
      "close": 323.9,
      "volume": 77481800,
      "adjClose": 323.9
    },
    {
      "date": "2025-08-21",
      "open": 322.08,
      "high": 324.9,
      "low": 318.68,
      "close": 320.11,
      "volume": 55744400,
      "adjClose": 320.11
    },
    {
      "date": "2025-08-22",
      "open": 321.66,
      "high": 340.25,
      "low": 319.69,
      "close": 340.01,
      "volume": 94016300,
      "adjClose": 340.01
    },
    {
      "date": "2025-08-25",
      "open": 338.9,
      "high": 349.53,
      "low": 335.03,
      "close": 346.6,
      "volume": 86670000,
      "adjClose": 346.6
    },
    {
      "date": "2025-08-26",
      "open": 344.93,
      "high": 351.9,
      "low": 343.72,
      "close": 351.67,
      "volume": 76651600,
      "adjClose": 351.67
    },
    {
      "date": "2025-08-27",
      "open": 351.94,
      "high": 355.39,
      "low": 349.16,
      "close": 349.6,
      "volume": 65519000,
      "adjClose": 349.6
    },
    {
      "date": "2025-08-28",
      "open": 350.91,
      "high": 353.55,
      "low": 340.26,
      "close": 345.98,
      "volume": 67903200,
      "adjClose": 345.98
    },
    {
      "date": "2025-08-29",
      "open": 347.23,
      "high": 348.75,
      "low": 331.7,
      "close": 333.87,
      "volume": 81145700,
      "adjClose": 333.87
    },
    {
      "date": "2025-09-02",
      "open": 328.23,
      "high": 333.33,
      "low": 325.6,
      "close": 329.36,
      "volume": 58392000,
      "adjClose": 329.36
    },
    {
      "date": "2025-09-03",
      "open": 335.2,
      "high": 343.33,
      "low": 328.51,
      "close": 334.09,
      "volume": 88733300,
      "adjClose": 334.09
    },
    {
      "date": "2025-09-04",
      "open": 336.15,
      "high": 338.89,
      "low": 331.48,
      "close": 338.53,
      "volume": 60711000,
      "adjClose": 338.53
    },
    {
      "date": "2025-09-05",
      "open": 348.0,
      "high": 355.87,
      "low": 344.68,
      "close": 350.84,
      "volume": 108989800,
      "adjClose": 350.84
    },
    {
      "date": "2025-09-08",
      "open": 354.64,
      "high": 358.44,
      "low": 344.84,
      "close": 346.4,
      "volume": 75208300,
      "adjClose": 346.4
    },
    {
      "date": "2025-09-09",
      "open": 348.44,
      "high": 350.77,
      "low": 343.82,
      "close": 346.97,
      "volume": 53816000,
      "adjClose": 346.97
    },
    {
      "date": "2025-09-10",
      "open": 350.55,
      "high": 356.33,
      "low": 346.07,
      "close": 347.79,
      "volume": 72121700,
      "adjClose": 347.79
    },
    {
      "date": "2025-09-11",
      "open": 350.17,
      "high": 368.99,
      "low": 347.6,
      "close": 368.81,
      "volume": 103756000,
      "adjClose": 368.81
    },
    {
      "date": "2025-09-12",
      "open": 370.94,
      "high": 396.69,
      "low": 370.24,
      "close": 395.94,
      "volume": 168156400,
      "adjClose": 395.94
    },
    {
      "date": "2025-09-15",
      "open": 423.13,
      "high": 425.7,
      "low": 402.43,
      "close": 410.04,
      "volume": 163823700,
      "adjClose": 410.04
    },
    {
      "date": "2025-09-16",
      "open": 414.5,
      "high": 423.25,
      "low": 411.43,
      "close": 421.62,
      "volume": 104285700,
      "adjClose": 421.62
    },
    {
      "date": "2025-09-17",
      "open": 415.75,
      "high": 428.31,
      "low": 409.67,
      "close": 425.86,
      "volume": 106133500,
      "adjClose": 425.86
    },
    {
      "date": "2025-09-18",
      "open": 428.87,
      "high": 432.22,
      "low": 416.56,
      "close": 416.85,
      "volume": 90454500,
      "adjClose": 416.85
    },
    {
      "date": "2025-09-19",
      "open": 421.82,
      "high": 429.47,
      "low": 421.72,
      "close": 426.07,
      "volume": 93131000,
      "adjClose": 426.07
    },
    {
      "date": "2025-09-22",
      "open": 431.11,
      "high": 444.98,
      "low": 429.13,
      "close": 434.21,
      "volume": 97108800,
      "adjClose": 434.21
    },
    {
      "date": "2025-09-23",
      "open": 439.88,
      "high": 440.97,
      "low": 423.72,
      "close": 425.85,
      "volume": 83422700,
      "adjClose": 425.85
    },
    {
      "date": "2025-09-24",
      "open": 429.83,
      "high": 444.21,
      "low": 429.03,
      "close": 442.79,
      "volume": 93133600,
      "adjClose": 442.79
    },
    {
      "date": "2025-09-25",
      "open": 435.24,
      "high": 435.35,
      "low": 419.08,
      "close": 423.39,
      "volume": 96746400,
      "adjClose": 423.39
    },
    {
      "date": "2025-09-26",
      "open": 428.3,
      "high": 440.47,
      "low": 421.02,
      "close": 440.4,
      "volume": 101628200,
      "adjClose": 440.4
    },
    {
      "date": "2025-09-29",
      "open": 444.35,
      "high": 450.98,
      "low": 439.5,
      "close": 443.21,
      "volume": 79491500,
      "adjClose": 443.21
    },
    {
      "date": "2025-09-30",
      "open": 441.52,
      "high": 445.0,
      "low": 433.12,
      "close": 444.72,
      "volume": 74358000,
      "adjClose": 444.72
    },
    {
      "date": "2025-10-01",
      "open": 443.8,
      "high": 462.29,
      "low": 440.75,
      "close": 459.46,
      "volume": 98122300,
      "adjClose": 459.46
    },
    {
      "date": "2025-10-02",
      "open": 470.54,
      "high": 470.75,
      "low": 435.57,
      "close": 436.0,
      "volume": 137009000,
      "adjClose": 436.0
    },
    {
      "date": "2025-10-03",
      "open": 443.29,
      "high": 446.77,
      "low": 416.58,
      "close": 429.83,
      "volume": 133188200,
      "adjClose": 429.83
    },
    {
      "date": "2025-10-06",
      "open": 440.75,
      "high": 453.55,
      "low": 436.69,
      "close": 453.25,
      "volume": 85324900,
      "adjClose": 453.25
    },
    {
      "date": "2025-10-07",
      "open": 447.82,
      "high": 452.68,
      "low": 432.45,
      "close": 433.09,
      "volume": 102296100,
      "adjClose": 433.09
    },
    {
      "date": "2025-10-08",
      "open": 437.57,
      "high": 441.33,
      "low": 425.23,
      "close": 438.69,
      "volume": 71192100,
      "adjClose": 438.69
    },
    {
      "date": "2025-10-09",
      "open": 431.81,
      "high": 436.35,
      "low": 426.18,
      "close": 435.54,
      "volume": 69339900,
      "adjClose": 435.54
    },
    {
      "date": "2025-10-10",
      "open": 436.54,
      "high": 443.13,
      "low": 411.45,
      "close": 413.49,
      "volume": 112107900,
      "adjClose": 413.49
    },
    {
      "date": "2025-10-13",
      "open": 423.53,
      "high": 436.89,
      "low": 419.7,
      "close": 435.9,
      "volume": 79552800,
      "adjClose": 435.9
    },
    {
      "date": "2025-10-14",
      "open": 426.79,
      "high": 434.2,
      "low": 417.86,
      "close": 429.24,
      "volume": 72669400,
      "adjClose": 429.24
    },
    {
      "date": "2025-10-15",
      "open": 434.9,
      "high": 440.51,
      "low": 426.33,
      "close": 435.15,
      "volume": 71558200,
      "adjClose": 435.15
    },
    {
      "date": "2025-10-16",
      "open": 434.73,
      "high": 439.35,
      "low": 421.31,
      "close": 428.75,
      "volume": 77189900,
      "adjClose": 428.75
    },
    {
      "date": "2025-10-17",
      "open": 425.5,
      "high": 441.46,
      "low": 423.6,
      "close": 439.31,
      "volume": 89331600,
      "adjClose": 439.31
    },
    {
      "date": "2025-10-20",
      "open": 443.87,
      "high": 449.8,
      "low": 440.61,
      "close": 447.43,
      "volume": 63719000,
      "adjClose": 447.43
    },
    {
      "date": "2025-10-21",
      "open": 445.76,
      "high": 449.3,
      "low": 442.05,
      "close": 442.6,
      "volume": 54412200,
      "adjClose": 442.6
    },
    {
      "date": "2025-10-22",
      "open": 443.45,
      "high": 445.54,
      "low": 429.0,
      "close": 438.97,
      "volume": 84023500,
      "adjClose": 438.97
    },
    {
      "date": "2025-10-23",
      "open": 420.0,
      "high": 449.4,
      "low": 413.9,
      "close": 448.98,
      "volume": 126709800,
      "adjClose": 448.98
    },
    {
      "date": "2025-10-24",
      "open": 446.83,
      "high": 451.68,
      "low": 430.17,
      "close": 433.72,
      "volume": 94727800,
      "adjClose": 433.72
    },
    {
      "date": "2025-10-27",
      "open": 439.98,
      "high": 460.16,
      "low": 438.69,
      "close": 452.42,
      "volume": 105867500,
      "adjClose": 452.42
    },
    {
      "date": "2025-10-28",
      "open": 454.78,
      "high": 467.0,
      "low": 451.6,
      "close": 460.55,
      "volume": 80185700,
      "adjClose": 460.55
    },
    {
      "date": "2025-10-29",
      "open": 462.5,
      "high": 465.7,
      "low": 452.65,
      "close": 461.51,
      "volume": 67983500,
      "adjClose": 461.51
    },
    {
      "date": "2025-10-30",
      "open": 451.05,
      "high": 455.06,
      "low": 439.61,
      "close": 440.1,
      "volume": 72447900,
      "adjClose": 440.1
    },
    {
      "date": "2025-10-31",
      "open": 446.75,
      "high": 458.0,
      "low": 443.69,
      "close": 456.56,
      "volume": 83135800,
      "adjClose": 456.56
    },
    {
      "date": "2025-11-03",
      "open": 455.99,
      "high": 474.07,
      "low": 453.8,
      "close": 468.37,
      "volume": 84595200,
      "adjClose": 468.37
    },
    {
      "date": "2025-11-04",
      "open": 454.46,
      "high": 460.22,
      "low": 443.6,
      "close": 444.26,
      "volume": 87756600,
      "adjClose": 444.26
    },
    {
      "date": "2025-11-05",
      "open": 452.05,
      "high": 466.33,
      "low": 440.71,
      "close": 462.07,
      "volume": 85573000,
      "adjClose": 462.07
    },
    {
      "date": "2025-11-06",
      "open": 461.96,
      "high": 467.45,
      "low": 435.09,
      "close": 445.91,
      "volume": 109622900,
      "adjClose": 445.91
    },
    {
      "date": "2025-11-07",
      "open": 437.92,
      "high": 439.36,
      "low": 421.88,
      "close": 429.52,
      "volume": 103471500,
      "adjClose": 429.52
    },
    {
      "date": "2025-11-10",
      "open": 439.6,
      "high": 449.67,
      "low": 433.36,
      "close": 445.23,
      "volume": 76515900,
      "adjClose": 445.23
    },
    {
      "date": "2025-11-11",
      "open": 439.4,
      "high": 442.49,
      "low": 432.36,
      "close": 439.62,
      "volume": 60533200,
      "adjClose": 439.62
    },
    {
      "date": "2025-11-12",
      "open": 442.15,
      "high": 442.33,
      "low": 426.56,
      "close": 430.6,
      "volume": 58513500,
      "adjClose": 430.6
    },
    {
      "date": "2025-11-13",
      "open": 423.13,
      "high": 424.5,
      "low": 396.34,
      "close": 401.99,
      "volume": 118948000,
      "adjClose": 401.99
    },
    {
      "date": "2025-11-14",
      "open": 386.3,
      "high": 412.19,
      "low": 382.78,
      "close": 404.35,
      "volume": 105506700,
      "adjClose": 404.35
    },
    {
      "date": "2025-11-17",
      "open": 398.74,
      "high": 423.96,
      "low": 398.74,
      "close": 408.92,
      "volume": 102214300,
      "adjClose": 408.92
    },
    {
      "date": "2025-11-18",
      "open": 405.38,
      "high": 408.9,
      "low": 393.71,
      "close": 401.25,
      "volume": 80688600,
      "adjClose": 401.25
    },
    {
      "date": "2025-11-19",
      "open": 406.18,
      "high": 411.78,
      "low": 398.5,
      "close": 403.99,
      "volume": 72047700,
      "adjClose": 403.99
    },
    {
      "date": "2025-11-20",
      "open": 414.63,
      "high": 428.94,
      "low": 394.74,
      "close": 395.23,
      "volume": 113548800,
      "adjClose": 395.23
    },
    {
      "date": "2025-11-21",
      "open": 402.32,
      "high": 402.8,
      "low": 383.76,
      "close": 391.09,
      "volume": 100460600,
      "adjClose": 391.09
    },
    {
      "date": "2025-11-24",
      "open": 402.17,
      "high": 421.72,
      "low": 401.09,
      "close": 417.78,
      "volume": 96806400,
      "adjClose": 417.78
    },
    {
      "date": "2025-11-25",
      "open": 414.42,
      "high": 420.48,
      "low": 405.95,
      "close": 419.4,
      "volume": 71915600,
      "adjClose": 419.4
    },
    {
      "date": "2025-11-26",
      "open": 423.95,
      "high": 426.94,
      "low": 416.89,
      "close": 426.58,
      "volume": 63463000,
      "adjClose": 426.58
    },
    {
      "date": "2025-11-28",
      "open": 426.59,
      "high": 432.93,
      "low": 426.2,
      "close": 430.17,
      "volume": 36252900,
      "adjClose": 430.17
    },
    {
      "date": "2025-12-01",
      "open": 425.32,
      "high": 433.66,
      "low": 425.29,
      "close": 430.14,
      "volume": 57463600,
      "adjClose": 430.14
    },
    {
      "date": "2025-12-02",
      "open": 430.81,
      "high": 436.8,
      "low": 422.12,
      "close": 429.24,
      "volume": 69336600,
      "adjClose": 429.24
    },
    {
      "date": "2025-12-03",
      "open": 432.1,
      "high": 447.92,
      "low": 431.11,
      "close": 446.74,
      "volume": 87483000,
      "adjClose": 446.74
    },
    {
      "date": "2025-12-04",
      "open": 449.94,
      "high": 454.63,
      "low": 445.39,
      "close": 454.53,
      "volume": 71906500,
      "adjClose": 454.53
    },
    {
      "date": "2025-12-05",
      "open": 453.03,
      "high": 458.87,
      "low": 451.66,
      "close": 455.0,
      "volume": 56427500,
      "adjClose": 455.0
    },
    {
      "date": "2025-12-08",
      "open": 447.45,
      "high": 449.75,
      "low": 435.25,
      "close": 439.58,
      "volume": 69165800,
      "adjClose": 439.58
    },
    {
      "date": "2025-12-09",
      "open": 437.54,
      "high": 452.39,
      "low": 435.7,
      "close": 445.17,
      "volume": 62367400,
      "adjClose": 445.17
    },
    {
      "date": "2025-12-10",
      "open": 446.07,
      "high": 456.88,
      "low": 443.61,
      "close": 451.45,
      "volume": 63257500,
      "adjClose": 451.45
    },
    {
      "date": "2025-12-11",
      "open": 448.95,
      "high": 449.27,
      "low": 440.33,
      "close": 446.89,
      "volume": 55979500,
      "adjClose": 446.89
    },
    {
      "date": "2025-12-12",
      "open": 448.09,
      "high": 463.01,
      "low": 441.67,
      "close": 458.96,
      "volume": 95656700,
      "adjClose": 458.96
    },
    {
      "date": "2025-12-15",
      "open": 469.44,
      "high": 481.77,
      "low": 467.66,
      "close": 475.31,
      "volume": 114542200,
      "adjClose": 475.31
    },
    {
      "date": "2025-12-16",
      "open": 472.21,
      "high": 491.5,
      "low": 465.83,
      "close": 489.88,
      "volume": 107608100,
      "adjClose": 489.88
    },
    {
      "date": "2025-12-17",
      "open": 488.22,
      "high": 495.28,
      "low": 466.2,
      "close": 467.26,
      "volume": 106490400,
      "adjClose": 467.26
    },
    {
      "date": "2025-12-18",
      "open": 478.16,
      "high": 490.86,
      "low": 473.12,
      "close": 483.37,
      "volume": 95168400,
      "adjClose": 483.37
    },
    {
      "date": "2025-12-19",
      "open": 488.12,
      "high": 490.49,
      "low": 474.72,
      "close": 481.2,
      "volume": 103305400,
      "adjClose": 481.2
    },
    {
      "date": "2025-12-22",
      "open": 489.88,
      "high": 498.83,
      "low": 485.33,
      "close": 488.73,
      "volume": 86916100,
      "adjClose": 488.73
    },
    {
      "date": "2025-12-23",
      "open": 489.4,
      "high": 491.97,
      "low": 482.84,
      "close": 485.56,
      "volume": 58223600,
      "adjClose": 485.56
    },
    {
      "date": "2025-12-24",
      "open": 488.48,
      "high": 490.9,
      "low": 476.8,
      "close": 485.4,
      "volume": 41285400,
      "adjClose": 485.4
    },
    {
      "date": "2025-12-26",
      "open": 485.23,
      "high": 489.09,
      "low": 473.82,
      "close": 475.19,
      "volume": 58780700,
      "adjClose": 475.19
    },
    {
      "date": "2025-12-29",
      "open": 469.0,
      "high": 469.4,
      "low": 459.0,
      "close": 459.64,
      "volume": 66263000,
      "adjClose": 459.64
    },
    {
      "date": "2025-12-30",
      "open": 461.09,
      "high": 463.12,
      "low": 453.83,
      "close": 454.43,
      "volume": 59238500,
      "adjClose": 454.43
    },
    {
      "date": "2025-12-31",
      "open": 456.1,
      "high": 456.55,
      "low": 449.3,
      "close": 449.72,
      "volume": 49078000,
      "adjClose": 449.72
    },
    {
      "date": "2026-01-02",
      "open": 457.8,
      "high": 458.34,
      "low": 435.3,
      "close": 438.07,
      "volume": 85263000,
      "adjClose": 438.07
    }
  ],
  "last_updated": "2026-01-04T13:45:07.484411",
  "change": 27.63,
  "change_percent": 6.73
}